{
	"backtraceGraph" : 
	{
		"commands" : 
		[
			"install"
		],
		"files" : 
		[
			"CMakeLists.txt"
		],
		"nodes" : 
		[
			{
				"file" : 0
			},
			{
				"command" : 0,
				"file" : 0,
				"line" : 53,
				"parent" : 0
			},
			{
				"command" : 0,
				"file" : 0,
				"line" : 59,
				"parent" : 0
			},
			{
				"command" : 0,
				"file" : 0,
				"line" : 71,
				"parent" : 0
			}
		]
	},
	"installers" : 
	[
		{
			"backtrace" : 1,
			"component" : "Unspecified",
			"destination" : "bin",
			"paths" : 
			[
				"demo.exe"
			],
			"targetId" : "demo::@6890427a1f51a3e7e1df",
			"targetIndex" : 0,
			"type" : "target"
		},
		{
			"backtrace" : 2,
			"component" : "Unspecified",
			"destination" : "bin",
			"type" : "importedRuntimeArtifacts"
		},
		{
			"backtrace" : 3,
			"component" : "Unspecified",
			"destination" : "share/demo/assets",
			"isOptional" : true,
			"paths" : 
			[
				{
					"from" : "assets",
					"to" : "."
				}
			],
			"type" : "directory"
		}
	],
	"paths" : 
	{
		"build" : ".",
		"source" : "."
	}
}
